mcsmc/Mcsm.py
mcsmc/__init__.py
mcsmc-0.0.3.dist-info/METADATA
mcsmc-0.0.3.dist-info/WHEEL
mcsmc-0.0.3.dist-info/top_level.txt
mcsmc-0.0.3.dist-info/RECORD
