Metadata-Version: 2.4
Name: mcsmc
Version: 0.0.3
Summary: mcsm面板控制库
Author-email: xiaoliang <2700858939@qq.com>
License: Apache 2.0
Project-URL: text, https://github.com/yxjsxl
Keywords: mcsm,minecraft,server,control
Classifier: Intended Audience :: Developers
Classifier: Operating System :: OS Independent
Classifier: Programming Language :: Python :: 3
Requires-Python: >=3.5
Requires-Dist: requests
